{
  "success": true,
  "data": [
    {
      "label": "TT  P. Sambu",
      "title": "TT  P. Sambu",
      "value": "1117",
      "html": "\u003Coption value=\u00221117\u0022\u003ETT  P. Sambu\u003C/option\u003E"
    },
    {
      "label": "Depot G. Sitoli",
      "title": "Depot G. Sitoli",
      "value": "1106",
      "html": "\u003Coption value=\u00221106\u0022\u003EDepot G. Sitoli\u003C/option\u003E"
    },
    {
      "label": "Depot Sibolga",
      "title": "Depot Sibolga",
      "value": "1105",
      "html": "\u003Coption value=\u00221105\u0022\u003EDepot Sibolga\u003C/option\u003E"
    },
    {
      "label": "Depot Kisaran",
      "title": "Depot Kisaran",
      "value": "1103",
      "html": "\u003Coption value=\u00221103\u0022\u003EDepot Kisaran\u003C/option\u003E"
    },
    {
      "label": "TT Teluk Kabung",
      "title": "TT Teluk Kabung",
      "value": "1112",
      "html": "\u003Coption value=\u00221112\u0022\u003ETT Teluk Kabung\u003C/option\u003E"
    },
    {
      "label": "Depot Meulaboh",
      "title": "Depot Meulaboh",
      "value": "1110",
      "html": "\u003Coption value=\u00221110\u0022\u003EDepot Meulaboh\u003C/option\u003E"
    },
    {
      "label": "Depot Simeulue",
      "title": "Depot Simeulue",
      "value": "1111",
      "html": "\u003Coption value=\u00221111\u0022\u003EDepot Simeulue\u003C/option\u003E"
    },
    {
      "label": "Depot P. Siantar",
      "title": "Depot P. Siantar",
      "value": "1104",
      "html": "\u003Coption value=\u00221104\u0022\u003EDepot P. Siantar\u003C/option\u003E"
    },
    {
      "label": "Depot Siak",
      "title": "Depot Siak",
      "value": "1113",
      "html": "\u003Coption value=\u00221113\u0022\u003EDepot Siak\u003C/option\u003E"
    },
    {
      "label": "Instalasi Medan Group",
      "title": "Instalasi Medan Group",
      "value": "1101",
      "html": "\u003Coption value=\u00221101\u0022\u003EInstalasi Medan Group\u003C/option\u003E"
    },
    {
      "label": "Depot Krueng Raya",
      "title": "Depot Krueng Raya",
      "value": "1109",
      "html": "\u003Coption value=\u00221109\u0022\u003EDepot Krueng Raya\u003C/option\u003E"
    },
    {
      "label": "Depot Kijang",
      "title": "Depot Kijang",
      "value": "1115",
      "html": "\u003Coption value=\u00221115\u0022\u003EDepot Kijang\u003C/option\u003E"
    },
    {
      "label": "Depot Tembilahan",
      "title": "Depot Tembilahan",
      "value": "1120",
      "html": "\u003Coption value=\u00221120\u0022\u003EDepot Tembilahan\u003C/option\u003E"
    },
    {
      "label": "Depot Batam",
      "title": "Depot Batam",
      "value": "5116",
      "html": "\u003Coption value=\u00225116\u0022\u003EDepot Batam\u003C/option\u003E"
    },
    {
      "label": "Depot Dumai",
      "title": "Depot Dumai",
      "value": "1114",
      "html": "\u003Coption value=\u00221114\u0022\u003EDepot Dumai\u003C/option\u003E"
    },
    {
      "label": "Depot Natuna Group",
      "title": "Depot Natuna Group",
      "value": "1119",
      "html": "\u003Coption value=\u00221119\u0022\u003EDepot Natuna Group\u003C/option\u003E"
    },
    {
      "label": "TT  T. Uban",
      "title": "TT  T. Uban",
      "value": "1118",
      "html": "\u003Coption value=\u00221118\u0022\u003ETT  T. Uban\u003C/option\u003E"
    },
    {
      "label": "Depot Sabang",
      "title": "Depot Sabang",
      "value": "1107",
      "html": "\u003Coption value=\u00221107\u0022\u003EDepot Sabang\u003C/option\u003E"
    },
    {
      "label": "Depot Lhok Seumawe",
      "title": "Depot Lhok Seumawe",
      "value": "1108",
      "html": "\u003Coption value=\u00221108\u0022\u003EDepot Lhok Seumawe\u003C/option\u003E"
    },
    {
      "label": "Depot Tg. Pandan P",
      "title": "Depot Tg. Pandan P",
      "value": "5128",
      "html": "\u003Coption value=\u00225128\u0022\u003EDepot Tg. Pandan P\u003C/option\u003E"
    },
    {
      "label": "Depot Jambi",
      "title": "Depot Jambi",
      "value": "1126",
      "html": "\u003Coption value=\u00221126\u0022\u003EDepot Jambi\u003C/option\u003E"
    },
    {
      "label": "Depot Pangkal Balam",
      "title": "Depot Pangkal Balam",
      "value": "1127",
      "html": "\u003Coption value=\u00221127\u0022\u003EDepot Pangkal Balam\u003C/option\u003E"
    },
    {
      "label": "Depot Kertapati",
      "title": "Depot Kertapati",
      "value": "1121",
      "html": "\u003Coption value=\u00221121\u0022\u003EDepot Kertapati\u003C/option\u003E"
    },
    {
      "label": "Depot Lahat",
      "title": "Depot Lahat",
      "value": "1124",
      "html": "\u003Coption value=\u00221124\u0022\u003EDepot Lahat\u003C/option\u003E"
    },
    {
      "label": "Depot Pulau Baai",
      "title": "Depot Pulau Baai",
      "value": "1129",
      "html": "\u003Coption value=\u00221129\u0022\u003EDepot Pulau Baai\u003C/option\u003E"
    },
    {
      "label": "Depot Baturaja",
      "title": "Depot Baturaja",
      "value": "1122",
      "html": "\u003Coption value=\u00221122\u0022\u003EDepot Baturaja\u003C/option\u003E"
    },
    {
      "label": "Depot Panjang",
      "title": "Depot Panjang",
      "value": "1123",
      "html": "\u003Coption value=\u00221123\u0022\u003EDepot Panjang\u003C/option\u003E"
    },
    {
      "label": "Depot Lubuk Linggau",
      "title": "Depot Lubuk Linggau",
      "value": "1125",
      "html": "\u003Coption value=\u00221125\u0022\u003EDepot Lubuk Linggau\u003C/option\u003E"
    },
    {
      "label": "Depot Ujung Berung",
      "title": "Depot Ujung Berung",
      "value": "1206",
      "html": "\u003Coption value=\u00221206\u0022\u003EDepot Ujung Berung\u003C/option\u003E"
    },
    {
      "label": "Depot Plumpang",
      "title": "Depot Plumpang",
      "value": "1202",
      "html": "\u003Coption value=\u00221202\u0022\u003EDepot Plumpang\u003C/option\u003E"
    },
    {
      "label": "TBBM Merak",
      "title": "TBBM Merak",
      "value": "1218",
      "html": "\u003Coption value=\u00221218\u0022\u003ETBBM Merak\u003C/option\u003E"
    },
    {
      "label": "TT Balongan",
      "title": "TT Balongan",
      "value": "1208",
      "html": "\u003Coption value=\u00221208\u0022\u003ETT Balongan\u003C/option\u003E"
    },
    {
      "label": "Depot Tasikmalaya",
      "title": "Depot Tasikmalaya",
      "value": "1207",
      "html": "\u003Coption value=\u00221207\u0022\u003EDepot Tasikmalaya\u003C/option\u003E"
    },
    {
      "label": "TT T.Gerem",
      "title": "TT T.Gerem",
      "value": "1201",
      "html": "\u003Coption value=\u00221201\u0022\u003ETT T.Gerem\u003C/option\u003E"
    },
    {
      "label": "Depot Cikampek",
      "title": "Depot Cikampek",
      "value": "1204",
      "html": "\u003Coption value=\u00221204\u0022\u003EDepot Cikampek\u003C/option\u003E"
    },
    {
      "label": "Depot Padalarang",
      "title": "Depot Padalarang",
      "value": "1205",
      "html": "\u003Coption value=\u00221205\u0022\u003EDepot Padalarang\u003C/option\u003E"
    },
    {
      "label": "Inst T Priok",
      "title": "Inst T Priok",
      "value": "5203",
      "html": "\u003Coption value=\u00225203\u0022\u003EInst T Priok\u003C/option\u003E"
    },
    {
      "label": "TBBM Semarang Group",
      "title": "TBBM Semarang Group",
      "value": "1210",
      "html": "\u003Coption value=\u00221210\u0022\u003ETBBM Semarang Group\u003C/option\u003E"
    },
    {
      "label": "Depot Rewulu",
      "title": "Depot Rewulu",
      "value": "1211",
      "html": "\u003Coption value=\u00221211\u0022\u003EDepot Rewulu\u003C/option\u003E"
    },
    {
      "label": "TBBM Semarang Group - Cepu",
      "title": "TBBM Semarang Group - Cepu",
      "value": "1217",
      "html": "\u003Coption value=\u00221217\u0022\u003ETBBM Semarang Group - Cepu\u003C/option\u003E"
    },
    {
      "label": "Depot Cilacap",
      "title": "Depot Cilacap",
      "value": "1215",
      "html": "\u003Coption value=\u00221215\u0022\u003EDepot Cilacap\u003C/option\u003E"
    },
    {
      "label": "TT Lomanis",
      "title": "TT Lomanis",
      "value": "1216",
      "html": "\u003Coption value=\u00221216\u0022\u003ETT Lomanis\u003C/option\u003E"
    },
    {
      "label": "Depot Boyolali",
      "title": "Depot Boyolali",
      "value": "1213",
      "html": "\u003Coption value=\u00221213\u0022\u003EDepot Boyolali\u003C/option\u003E"
    },
    {
      "label": "Depot Maos",
      "title": "Depot Maos",
      "value": "1214",
      "html": "\u003Coption value=\u00221214\u0022\u003EDepot Maos\u003C/option\u003E"
    },
    {
      "label": "Depot Tegal",
      "title": "Depot Tegal",
      "value": "1219",
      "html": "\u003Coption value=\u00221219\u0022\u003EDepot Tegal\u003C/option\u003E"
    },
    {
      "label": "Depot Badas",
      "title": "Depot Badas",
      "value": "1311",
      "html": "\u003Coption value=\u00221311\u0022\u003EDepot Badas\u003C/option\u003E"
    },
    {
      "label": "Depot Waingapu",
      "title": "Depot Waingapu",
      "value": "1316",
      "html": "\u003Coption value=\u00221316\u0022\u003EDepot Waingapu\u003C/option\u003E"
    },
    {
      "label": "Depot Madiun",
      "title": "Depot Madiun",
      "value": "1304",
      "html": "\u003Coption value=\u00221304\u0022\u003EDepot Madiun\u003C/option\u003E"
    },
    {
      "label": "Depot Tanjung Wangi",
      "title": "Depot Tanjung Wangi",
      "value": "1307",
      "html": "\u003Coption value=\u00221307\u0022\u003EDepot Tanjung Wangi\u003C/option\u003E"
    },
    {
      "label": "Depot Kupang",
      "title": "Depot Kupang",
      "value": "1318",
      "html": "\u003Coption value=\u00221318\u0022\u003EDepot Kupang\u003C/option\u003E"
    },
    {
      "label": "Depot Maumere",
      "title": "Depot Maumere",
      "value": "1315",
      "html": "\u003Coption value=\u00221315\u0022\u003EDepot Maumere\u003C/option\u003E"
    },
    {
      "label": "Depot Reo",
      "title": "Depot Reo",
      "value": "1313",
      "html": "\u003Coption value=\u00221313\u0022\u003EDepot Reo\u003C/option\u003E"
    },
    {
      "label": "TTU Tuban",
      "title": "TTU Tuban",
      "value": "1322",
      "html": "\u003Coption value=\u00221322\u0022\u003ETTU Tuban\u003C/option\u003E"
    },
    {
      "label": "Depot Malang",
      "title": "Depot Malang",
      "value": "1303",
      "html": "\u003Coption value=\u00221303\u0022\u003EDepot Malang\u003C/option\u003E"
    },
    {
      "label": "Depot Larantuka",
      "title": "Depot Larantuka",
      "value": "1317",
      "html": "\u003Coption value=\u00221317\u0022\u003EDepot Larantuka\u003C/option\u003E"
    },
    {
      "label": "Depot Atapupu",
      "title": "Depot Atapupu",
      "value": "1319",
      "html": "\u003Coption value=\u00221319\u0022\u003EDepot Atapupu\u003C/option\u003E"
    },
    {
      "label": "Depot Bima",
      "title": "Depot Bima",
      "value": "1312",
      "html": "\u003Coption value=\u00221312\u0022\u003EDepot Bima\u003C/option\u003E"
    },
    {
      "label": "TT Manggis",
      "title": "TT Manggis",
      "value": "1309",
      "html": "\u003Coption value=\u00221309\u0022\u003ETT Manggis\u003C/option\u003E"
    },
    {
      "label": "Depot Benoa/Sanggaran",
      "title": "Depot Benoa/Sanggaran",
      "value": "1308",
      "html": "\u003Coption value=\u00221308\u0022\u003EDepot Benoa/Sanggaran\u003C/option\u003E"
    },
    {
      "label": "Depot Ampenan",
      "title": "Depot Ampenan",
      "value": "1310",
      "html": "\u003Coption value=\u00221310\u0022\u003EDepot Ampenan\u003C/option\u003E"
    },
    {
      "label": "Depot Ende",
      "title": "Depot Ende",
      "value": "1314",
      "html": "\u003Coption value=\u00221314\u0022\u003EDepot Ende\u003C/option\u003E"
    },
    {
      "label": "Inst. Surabaya",
      "title": "Inst. Surabaya",
      "value": "1306",
      "html": "\u003Coption value=\u00221306\u0022\u003EInst. Surabaya\u003C/option\u003E"
    },
    {
      "label": "Depot Camplong",
      "title": "Depot Camplong",
      "value": "1301",
      "html": "\u003Coption value=\u00221301\u0022\u003EDepot Camplong\u003C/option\u003E"
    },
    {
      "label": "Depot Kalabahi",
      "title": "Depot Kalabahi",
      "value": "1320",
      "html": "\u003Coption value=\u00221320\u0022\u003EDepot Kalabahi\u003C/option\u003E"
    },
    {
      "label": "Depot Pangkalan Bun",
      "title": "Depot Pangkalan Bun",
      "value": "1407",
      "html": "\u003Coption value=\u00221407\u0022\u003EDepot Pangkalan Bun\u003C/option\u003E"
    },
    {
      "label": "Depot Kotabaru",
      "title": "Depot Kotabaru",
      "value": "1405",
      "html": "\u003Coption value=\u00221405\u0022\u003EDepot Kotabaru\u003C/option\u003E"
    },
    {
      "label": "Depot Jobber Ketapang",
      "title": "Depot Jobber Ketapang",
      "value": "1411",
      "html": "\u003Coption value=\u00221411\u0022\u003EDepot Jobber Ketapang\u003C/option\u003E"
    },
    {
      "label": "Depot Pontianak",
      "title": "Depot Pontianak",
      "value": "1409",
      "html": "\u003Coption value=\u00221409\u0022\u003EDepot Pontianak\u003C/option\u003E"
    },
    {
      "label": "Depot Sampit",
      "title": "Depot Sampit",
      "value": "1408",
      "html": "\u003Coption value=\u00221408\u0022\u003EDepot Sampit\u003C/option\u003E"
    },
    {
      "label": "Depot Jobber Berau",
      "title": "Depot Jobber Berau",
      "value": "1452",
      "html": "\u003Coption value=\u00221452\u0022\u003EDepot Jobber Berau\u003C/option\u003E"
    },
    {
      "label": "Depot Banjarmasin",
      "title": "Depot Banjarmasin",
      "value": "1404",
      "html": "\u003Coption value=\u00221404\u0022\u003EDepot Banjarmasin\u003C/option\u003E"
    },
    {
      "label": "Depot Pulang Pisau",
      "title": "Depot Pulang Pisau",
      "value": "1406",
      "html": "\u003Coption value=\u00221406\u0022\u003EDepot Pulang Pisau\u003C/option\u003E"
    },
    {
      "label": "Depot Tarakan",
      "title": "Depot Tarakan",
      "value": "1403",
      "html": "\u003Coption value=\u00221403\u0022\u003EDepot Tarakan\u003C/option\u003E"
    },
    {
      "label": "Depot Samarinda",
      "title": "Depot Samarinda",
      "value": "1402",
      "html": "\u003Coption value=\u00221402\u0022\u003EDepot Samarinda\u003C/option\u003E"
    },
    {
      "label": "Depot Jobber Sanggau",
      "title": "Depot Jobber Sanggau",
      "value": "1453",
      "html": "\u003Coption value=\u00221453\u0022\u003EDepot Jobber Sanggau\u003C/option\u003E"
    },
    {
      "label": "Depot Balikpapan",
      "title": "Depot Balikpapan",
      "value": "1401",
      "html": "\u003Coption value=\u00221401\u0022\u003EDepot Balikpapan\u003C/option\u003E"
    },
    {
      "label": "TBBM Pulau Laut",
      "title": "TBBM Pulau Laut",
      "value": "1454",
      "html": "\u003Coption value=\u00221454\u0022\u003ETBBM Pulau Laut\u003C/option\u003E"
    },
    {
      "label": "Depot Sintang",
      "title": "Depot Sintang",
      "value": "1410",
      "html": "\u003Coption value=\u00221410\u0022\u003EDepot Sintang\u003C/option\u003E"
    },
    {
      "label": "Inst. Makassar",
      "title": "Inst. Makassar",
      "value": "1412",
      "html": "\u003Coption value=\u00221412\u0022\u003EInst. Makassar\u003C/option\u003E"
    },
    {
      "label": "Depot Kendari",
      "title": "Depot Kendari",
      "value": "1415",
      "html": "\u003Coption value=\u00221415\u0022\u003EDepot Kendari\u003C/option\u003E"
    },
    {
      "label": "Depot Moutong",
      "title": "Depot Moutong",
      "value": "1421",
      "html": "\u003Coption value=\u00221421\u0022\u003EDepot Moutong\u003C/option\u003E"
    },
    {
      "label": "Depot Luwuk",
      "title": "Depot Luwuk",
      "value": "1427",
      "html": "\u003Coption value=\u00221427\u0022\u003EDepot Luwuk\u003C/option\u003E"
    },
    {
      "label": "Depot Gorontalo",
      "title": "Depot Gorontalo",
      "value": "1420",
      "html": "\u003Coption value=\u00221420\u0022\u003EDepot Gorontalo\u003C/option\u003E"
    },
    {
      "label": "Depot Pare-Pare",
      "title": "Depot Pare-Pare",
      "value": "1413",
      "html": "\u003Coption value=\u00221413\u0022\u003EDepot Pare-Pare\u003C/option\u003E"
    },
    {
      "label": "Depot Kolonedale",
      "title": "Depot Kolonedale",
      "value": "1429",
      "html": "\u003Coption value=\u00221429\u0022\u003EDepot Kolonedale\u003C/option\u003E"
    },
    {
      "label": "Depot Banggai",
      "title": "Depot Banggai",
      "value": "1428",
      "html": "\u003Coption value=\u00221428\u0022\u003EDepot Banggai\u003C/option\u003E"
    },
    {
      "label": "Depot Bitung",
      "title": "Depot Bitung",
      "value": "1419",
      "html": "\u003Coption value=\u00221419\u0022\u003EDepot Bitung\u003C/option\u003E"
    },
    {
      "label": "Depot Tahuna",
      "title": "Depot Tahuna",
      "value": "1430",
      "html": "\u003Coption value=\u00221430\u0022\u003EDepot Tahuna\u003C/option\u003E"
    },
    {
      "label": "Depot Palopo",
      "title": "Depot Palopo",
      "value": "1414",
      "html": "\u003Coption value=\u00221414\u0022\u003EDepot Palopo\u003C/option\u003E"
    },
    {
      "label": "Depot Poso",
      "title": "Depot Poso",
      "value": "1425",
      "html": "\u003Coption value=\u00221425\u0022\u003EDepot Poso\u003C/option\u003E"
    },
    {
      "label": "Depot Baubau",
      "title": "Depot Baubau",
      "value": "1416",
      "html": "\u003Coption value=\u00221416\u0022\u003EDepot Baubau\u003C/option\u003E"
    },
    {
      "label": "Depot Raha",
      "title": "Depot Raha",
      "value": "1417",
      "html": "\u003Coption value=\u00221417\u0022\u003EDepot Raha\u003C/option\u003E"
    },
    {
      "label": "Depot Kolaka",
      "title": "Depot Kolaka",
      "value": "1418",
      "html": "\u003Coption value=\u00221418\u0022\u003EDepot Kolaka\u003C/option\u003E"
    },
    {
      "label": "Depot Donggala / Palu",
      "title": "Depot Donggala / Palu",
      "value": "1423",
      "html": "\u003Coption value=\u00221423\u0022\u003EDepot Donggala / Palu\u003C/option\u003E"
    },
    {
      "label": "Depot Toli-Toli",
      "title": "Depot Toli-Toli",
      "value": "1422",
      "html": "\u003Coption value=\u00221422\u0022\u003EDepot Toli-Toli\u003C/option\u003E"
    },
    {
      "label": "Depot Namlea",
      "title": "Depot Namlea",
      "value": "1445",
      "html": "\u003Coption value=\u00221445\u0022\u003EDepot Namlea\u003C/option\u003E"
    },
    {
      "label": "Depot Manokwari",
      "title": "Depot Manokwari",
      "value": "1434",
      "html": "\u003Coption value=\u00221434\u0022\u003EDepot Manokwari\u003C/option\u003E"
    },
    {
      "label": "Depot Kaimana",
      "title": "Depot Kaimana",
      "value": "1439",
      "html": "\u003Coption value=\u00221439\u0022\u003EDepot Kaimana\u003C/option\u003E"
    },
    {
      "label": "Depot Jayapura",
      "title": "Depot Jayapura",
      "value": "1432",
      "html": "\u003Coption value=\u00221432\u0022\u003EDepot Jayapura\u003C/option\u003E"
    },
    {
      "label": "Depot Ternate",
      "title": "Depot Ternate",
      "value": "1447",
      "html": "\u003Coption value=\u00221447\u0022\u003EDepot Ternate\u003C/option\u003E"
    },
    {
      "label": "Depot Nabire",
      "title": "Depot Nabire",
      "value": "1438",
      "html": "\u003Coption value=\u00221438\u0022\u003EDepot Nabire\u003C/option\u003E"
    },
    {
      "label": "Depot Sorong",
      "title": "Depot Sorong",
      "value": "1433",
      "html": "\u003Coption value=\u00221433\u0022\u003EDepot Sorong\u003C/option\u003E"
    },
    {
      "label": "Depot Dobo",
      "title": "Depot Dobo",
      "value": "1450",
      "html": "\u003Coption value=\u00221450\u0022\u003EDepot Dobo\u003C/option\u003E"
    },
    {
      "label": "Depot Tobelo",
      "title": "Depot Tobelo",
      "value": "1449",
      "html": "\u003Coption value=\u00221449\u0022\u003EDepot Tobelo\u003C/option\u003E"
    },
    {
      "label": "Depot Jobber Timika",
      "title": "Depot Jobber Timika",
      "value": "1451",
      "html": "\u003Coption value=\u00221451\u0022\u003EDepot Jobber Timika\u003C/option\u003E"
    },
    {
      "label": "Depot Masohi",
      "title": "Depot Masohi",
      "value": "1442",
      "html": "\u003Coption value=\u00221442\u0022\u003EDepot Masohi\u003C/option\u003E"
    },
    {
      "label": "Depot Bula",
      "title": "Depot Bula",
      "value": "1443",
      "html": "\u003Coption value=\u00221443\u0022\u003EDepot Bula\u003C/option\u003E"
    },
    {
      "label": "TT Wayame",
      "title": "TT Wayame",
      "value": "1440",
      "html": "\u003Coption value=\u00221440\u0022\u003ETT Wayame\u003C/option\u003E"
    },
    {
      "label": "Depot Merauke",
      "title": "Depot Merauke",
      "value": "1437",
      "html": "\u003Coption value=\u00221437\u0022\u003EDepot Merauke\u003C/option\u003E"
    },
    {
      "label": "Depot Serui",
      "title": "Depot Serui",
      "value": "1435",
      "html": "\u003Coption value=\u00221435\u0022\u003EDepot Serui\u003C/option\u003E"
    },
    {
      "label": "Depot Tual",
      "title": "Depot Tual",
      "value": "1441",
      "html": "\u003Coption value=\u00221441\u0022\u003EDepot Tual\u003C/option\u003E"
    },
    {
      "label": "Depot Labuha",
      "title": "Depot Labuha",
      "value": "1446",
      "html": "\u003Coption value=\u00221446\u0022\u003EDepot Labuha\u003C/option\u003E"
    },
    {
      "label": "Depot Fak-Fak",
      "title": "Depot Fak-Fak",
      "value": "1436",
      "html": "\u003Coption value=\u00221436\u0022\u003EDepot Fak-Fak\u003C/option\u003E"
    },
    {
      "label": "Depot Sanana",
      "title": "Depot Sanana",
      "value": "1448",
      "html": "\u003Coption value=\u00221448\u0022\u003EDepot Sanana\u003C/option\u003E"
    },
    {
      "label": "Depot Biak",
      "title": "Depot Biak",
      "value": "1431",
      "html": "\u003Coption value=\u00221431\u0022\u003EDepot Biak\u003C/option\u003E"
    },
    {
      "label": "Depot Saumlaki",
      "title": "Depot Saumlaki",
      "value": "1444",
      "html": "\u003Coption value=\u00221444\u0022\u003EDepot Saumlaki\u003C/option\u003E"
    }
  ],
  "role": "top"
}
